<?xml version="1.0" encoding="UTF-8"?>
<AanleveringInformatieObject xmlns="https://standaarden.overheid.nl/lvbb/stop/aanlevering/"
                             schemaversie="1.1.0">
  <InformatieObjectVersie>
      <ExpressionIdentificatie xmlns="https://standaarden.overheid.nl/stop/imop/data/">
         <FRBRWork>/join/id/regdata/gm0037/2019/Zone_A</FRBRWork>
         <FRBRExpression>/join/id/regdata/gm0037/2019/Zone_A/nld@2019-06-18;3520</FRBRExpression>
         <soortWork>/join/id/stop/work_010</soortWork>
      </ExpressionIdentificatie>
      <InformatieObjectVersieMetadata xmlns="https://standaarden.overheid.nl/stop/imop/data/">
         <heeftGeboorteregeling>/akn/nl/act/gm0037/2019/reg456</heeftGeboorteregeling>
         <heeftBestanden>
            <heeftBestand>
               <Bestand>
                  <bestandsnaam>Zone_A.gml</bestandsnaam>
                 <hash>445a47bbc566951c0f46350a27788e684a7e606b73c4d58a0d98e91ec2ca78f12f893cebe97c8e3260089cbbe9a79c4b15fd5eba0eb2545c383d5384772daad5</hash>
               </Bestand>
            </heeftBestand>
         </heeftBestanden>
      </InformatieObjectVersieMetadata>
      <InformatieObjectMetadata xmlns="https://standaarden.overheid.nl/stop/imop/data/">
         <eindverantwoordelijke>/tooi/id/gemeente/gm0037</eindverantwoordelijke>
         <maker>/tooi/id/gemeente/gm0037</maker>
         <alternatieveTitels>
            <alternatieveTitel>Zone_A</alternatieveTitel>
         </alternatieveTitels>
         <naamInformatieObject>Zone_A</naamInformatieObject>
         <officieleTitel>/join/id/regdata/gm0037/2019/Zone_A</officieleTitel>
         <publicatieinstructie>TeConsolideren</publicatieinstructie>
         <formaatInformatieobject>/join/id/stop/informatieobject/gio_002</formaatInformatieobject>
      </InformatieObjectMetadata>
  </InformatieObjectVersie>
</AanleveringInformatieObject>
